ninja_extra/__init__.py
ninja_extra/apps.py
ninja_extra/compatible.py
ninja_extra/constants.py
ninja_extra/dependency_resolver.py
ninja_extra/details.py
ninja_extra/exceptions.py
ninja_extra/generic.py
ninja_extra/helper.py
ninja_extra/lazy.py
ninja_extra/logger.py
ninja_extra/main.py
ninja_extra/modules.py
ninja_extra/operation.py
ninja_extra/pagination.py
ninja_extra/py.typed
ninja_extra/router.py
ninja_extra/shortcuts.py
ninja_extra/signals.py
ninja_extra/status.py
ninja_extra/types.py
ninja_extra/urls.py
ninja_extra/conf/__init__.py
ninja_extra/conf/settings.py
ninja_extra/controllers/__init__.py
ninja_extra/controllers/base.py
ninja_extra/controllers/registry.py
ninja_extra/controllers/response.py
ninja_extra/controllers/route/__init__.py
ninja_extra/controllers/route/context.py
ninja_extra/controllers/route/route_functions.py
ninja_extra/permissions/__init__.py
ninja_extra/permissions/base.py
ninja_extra/permissions/common.py
ninja_extra/schemas/__init__.py
ninja_extra/schemas/response.py
ninja_extra/security/__init__.py
ninja_extra/security/api_key.py
ninja_extra/security/http.py
ninja_extra/security/session.py
ninja_extra/testing/__init__.py
ninja_extra/testing/client.py
ninja_extra/throttling/__init__.py
ninja_extra/throttling/decorator.py
ninja_extra/throttling/model.py
django_ninja_extra_easy-0.15.6.dist-info/LICENSE
django_ninja_extra_easy-0.15.6.dist-info/WHEEL
django_ninja_extra_easy-0.15.6.dist-info/METADATA
django_ninja_extra_easy-0.15.6.dist-info/RECORD
